src/SIP_Recordings/Start_SIP_recordings.py
src/SIP_Recordings/Stop_SIP_recordings.py
src/SIP_Recordings/__init__.py
SIP_Recordings-0.0.1.dist-info/LICENSE
SIP_Recordings-0.0.1.dist-info/METADATA
SIP_Recordings-0.0.1.dist-info/WHEEL
SIP_Recordings-0.0.1.dist-info/top_level.txt
SIP_Recordings-0.0.1.dist-info/RECORD
