Metadata-Version: 2.1
Name: SIP-Recordings
Version: 0.0.1
Summary: Scripts to start and stop multiple SIP recordings at the same time using Vbrick Rev.
Author-email: Alex McIntosh <alex.mcintosh@vbrick.com>
Classifier: Programming Language :: Python :: 3
Classifier: License :: OSI Approved :: MIT License
Classifier: Operating System :: OS Independent
Requires-Python: >=3.10
License-File: LICENSE
